Firmware/Ny TX/fifo_tx/src/fifo_tx.vhd
library ieee; 
use ieee.std_logic_1164.all; 
use ieee.numeric_std.all; 

entity fifo_tx is 
    generic ( 
        DATA_WIDTH : positive := 8;  -- Storage value (8-bit)
        FIFO_DEPTH : positive := 16  -- Addresse (Index)
    ); 

    port (
        clk : in std_logic; 
        rst_n : in std_logic; -- active high

        -- Write 
        wr_en   : in std_logic; 
        din     : in std_logic_vector(DATA_WIDTH-1 downto 0); 

        -- Read
        rd_en   : in std_logic; 
        dout    : out std_logic_vector(DATA_WIDTH-1 downto 0); 

        -- Status 
        empty   : out std_logic;
        full    : out std_logic
    ); 
end entity fifo_tx; 


architecture rtl of fifo_tx is 

    -- FIFO storage (ringbuffer)
    type mem_type is array (0 to FIFO_DEPTH - 1) of std_logic_vector(DATA_WIDTH - 1 downto 0); 
    signal mem : mem_type; 

    -- Write pointer
    signal w_ptr : unsigned(7 downto 0) := (others => '0'); 

    -- Read pointer
    signal r_ptr : unsigned(7 downto 0) := (others => '0'); 

    -- Counter for entry
    signal count : unsigned(8 downto 0) := (others => '0'); 


    
begin 

    -- Output
    dout <= mem(to_integer(r_ptr)); 
    empty <= '1' when count = 0 else '0'; 
    full <= '1' when count = FIFO_DEPTH else '0'; 

    -- Write/ Read Logic 
    process(clk)
    begin
        if rising_edge(clk) then

            if rst_n = '1' then 
                w_ptr <= (others => '0'); 
                r_ptr <= (others => '0');
                count <= (others => '0'); 

            else

                -- Write
                if (wr_en = '1') and (count < FIFO_DEPTH) then
                    mem(to_integer(w_ptr)) <= din; 
                    
                    if w_ptr = FIFO_DEPTH -1 then
                        w_ptr <= (others => '0'); 
                    else
                        w_ptr <= w_ptr +1; 
                    end if; 


                    if rd_en = '0'and count < FIFO_DEPTH then
                        count <= count + 1; 
                    end if;
                end if; 

                -- Read
                if (rd_en = '1') and (count > 0) then 
                    
                    if r_ptr = FIFO_DEPTH -1 then 
                        r_ptr <= (others => '0'); 
                    else
                        r_ptr <= r_ptr +1; 
                    end if; 


                    if wr_en = '0' then 
                        count <= count - 1; 
                    end if; 
                end if; 

            end if; 
        end if;

    end process;
end architecture;

Firmware/Tx/fifo_tx/tb/fifo_tx_tb.vhd
library ieee;
use ieee.std_logic_1164.all;
use ieee.numeric_std.all;

entity fifo_tx_tb is
end entity;

architecture sim of fifo_tx_tb is

    -- Testbench signals
    signal clk     : std_logic := '0';
    signal rst_n     : std_logic := '0'; -- aktic high

    signal wr_en   : std_logic := '0';
    signal rd_en   : std_logic := '0';

    signal din     : std_logic_vector(7 downto 0) := (others => '0');
    signal dout    : std_logic_vector(7 downto 0);

    signal empty   : std_logic;
    signal full    : std_logic;

    constant CLK_PERIOD : time := 20 ns;

begin

    --------------------------------------------------------------------
    -- DUT: FIFO
    --------------------------------------------------------------------
    uut : entity work.fifo_tx
        generic map (
            DATA_WIDTH => 8,
            FIFO_DEPTH => 4     -- liten FIFO → lett å teste wrap-around
        )
        port map (
            clk   => clk,
            rst_n   => rst_N,
            wr_en => wr_en,
            din   => din,
            rd_en => rd_en,
            dout  => dout,
            empty => empty,
            full  => full
        );

    --------------------------------------------------------------------
    -- Clock generator (50 MHz)
    --------------------------------------------------------------------
    clk_process : process
    begin
        clk <= '0';
        wait for CLK_PERIOD/2;
        clk <= '1';
        wait for CLK_PERIOD/2;
    end process;

    --------------------------------------------------------------------
    -- Test process
    --------------------------------------------------------------------
    stim : process
    begin
        ----------------------------------------------------------------
        -- RESET
        ----------------------------------------------------------------
        rst_n <= '1';
        wait for 40 ns;
        rst_n <= '0';
        wait for 40 ns;

        assert empty = '1'; 
        report "FIFO should be empty after reset" severity error;

        ----------------------------------------------------------------
        -- WRITE 3 VALUES
        ----------------------------------------------------------------
        report "Writing values A0, B1, C2";

        wr_en <= '1'; -- enable write to fifo
        din <= x"A0"; wait until rising_edge(clk);
        din <= x"B1"; wait until rising_edge(clk);
        din <= x"C2"; wait until rising_edge(clk);
        wr_en <= '0'; -- diable write to fifo

        wait for 1 ns;

        assert empty = '0' report "FIFO should NOT be empty" severity error;
        assert full  = '0' report "FIFO should NOT be full yet" severity error;

        ----------------------------------------------------------------
        -- READ BACK 3 VALUES
        ----------------------------------------------------------------
        report "Reading values (expect: A0, B1, C2)";

        rd_en <= '1'; wait until rising_edge(clk);
        assert dout = x"A0" report "Expected A0" severity error;

        wait until rising_edge(clk);
        assert dout = x"B1" report "Expected B1" severity error;

        wait until rising_edge(clk);
        assert dout = x"C2" report "Expected C2" severity error;

        rd_en <= '0';
        wait for 1 ns;

        assert empty = '1' report "FIFO should be empty now" severity error;

        ----------------------------------------------------------------
        -- TEST WRAP-AROUND
        ----------------------------------------------------------------
        report "Testing wrap-around";

        -- write 4 values (fills FIFO)
        wr_en <= '1';
        din <= x"11"; wait until rising_edge(clk);
        din <= x"22"; wait until rising_edge(clk);
        din <= x"33"; wait until rising_edge(clk);
        din <= x"44"; wait until rising_edge(clk);
        wr_en <= '0';

        assert full = '1' report "FIFO should be FULL after 4 writes" severity error;

        -- read one
        rd_en <= '1'; wait until rising_edge(clk);
        rd_en <= '0';

        assert full = '0' report "FIFO should NOT be full after 1 read" severity error;

        -- write again → should wrap correctly
        wr_en <= '1';
        din <= x"55";
        wait until rising_edge(clk);
        wr_en <= '0';

        ----------------------------------------------------------------
        -- FINISH
        ----------------------------------------------------------------
        report "FIFO test PASSED!" severity note;
        std.env.stop;
        wait;

    end process;

end architecture sim;

Firmware/Tx/fifo_tx/build/wave.vcd
$date
  Sun Nov 30 15:18:37 2025
$end
$version
  GHDL v0
$end
$timescale
  1 fs
$end
$scope module standard $end
$upscope $end
$scope module textio $end
$upscope $end
$scope module std_logic_1164 $end
$upscope $end
$scope module numeric_std $end
$upscope $end
$scope module env $end
$upscope $end
$scope module fifo_tx_tb $end
$var reg 1 ! clk $end
$var reg 1 " rst_n $end
$var reg 1 # wr_en $end
$var reg 1 $ rd_en $end
$var reg 8 % din[7:0] $end
$var reg 8 & dout[7:0] $end
$var reg 1 ' empty $end
$var reg 1 ( full $end
$scope module uut $end
$var reg 1 ) clk $end
$var reg 1 * rst_n $end
$var reg 1 + wr_en $end
$var reg 8 , din[7:0] $end
$var reg 1 - rd_en $end
$var reg 8 . dout[7:0] $end
$var reg 1 / empty $end
$var reg 1 0 full $end
$comment mem is not handled $end
$var reg 8 1 w_ptr[7:0] $end
$var reg 8 2 r_ptr[7:0] $end
$var reg 9 3 count[8:0] $end
$upscope $end
$upscope $end
$enddefinitions $end
#0
0!
1"
0#
0$
b00000000 %
bUUUUUUUU &
1'
0(
0)
1*
0+
b00000000 ,
0-
bUUUUUUUU .
1/
00
b00000000 1
b00000000 2
b000000000 3
#10000000
1!
1)
#20000000
0!
0)
#30000000
1!
1)
#40000000
0!
0"
0)
0*
#50000000
1!
1)
#60000000
0!
0)
#70000000
1!
1)
#80000000
0!
1#
b10100000 %
0)
1+
b10100000 ,
#90000000
1!
b10110001 %
b10100000 &
0'
1)
b10110001 ,
b10100000 .
0/
b00000001 1
b000000001 3
#100000000
0!
0)
#110000000
1!
b11000010 %
1)
b11000010 ,
b00000010 1
b000000010 3
#120000000
0!
0)
#130000000
1!
0#
1)
0+
b00000011 1
b000000011 3
#131000000
1$
1-
#140000000
0!
0)
#150000000
1!
b10110001 &
1)
b10110001 .
b00000001 2
b000000010 3
#160000000
0!
0)
#170000000
1!
b11000010 &
1)
b11000010 .
b00000010 2
b000000001 3
#180000000
0!
0)
#190000000
1!
0$
bUUUUUUUU &
1'
1)
0-
bUUUUUUUU .
1/
b00000011 2
b000000000 3
#191000000
1#
b00010001 %
1+
b00010001 ,
#200000000
0!
0)
#210000000
1!
b00100010 %
b00010001 &
0'
1)
b00100010 ,
b00010001 .
0/
b00000000 1
b000000001 3
#220000000
0!
0)
#230000000
1!
b00110011 %
1)
b00110011 ,
b00000001 1
b000000010 3
#240000000
0!
0)
#250000000
1!
b01000100 %
1)
b01000100 ,
b00000010 1
b000000011 3
#260000000
0!
0)
#270000000
1!
0#
1$
1(
1)
0+
1-
10
b00000011 1
b000000100 3
#280000000
0!
0)
#290000000
1!
1#
0$
b01010101 %
b00100010 &
0(
1)
1+
b01010101 ,
0-
b00100010 .
00
b00000000 2
b000000011 3
